{
  "priority": 69421,
  "panel": "obscure_tooltips:sf5_cyan",
  "icon": "obscure_tooltips:sf5_cyan",
  "effects": ["obscure_tooltips:sf5_cyan"],
  "filter": {
    "items": [
      "additionallanterns:oxidized_copper_chain",
      "additionallanterns:waxed_oxidized_copper_chain",
      "ae2:cyan_paint_ball",
      "biggerreactors:cyanite_block",
      "biggerreactors:cyanite_dust",
      "biggerreactors:cyanite_ingot",
      "colouredstuff:brick_brown",
      "colouredstuff:brick_cyan",
      "colouredstuff:chiseled_sandstone_cyan",
      "colouredstuff:chiseled_stone_bricks_cyan",
      "colouredstuff:cobblestone_cyan",
      "colouredstuff:crafting_table_cyan",
      "colouredstuff:cut_sandstone_cyan",
      "colouredstuff:dirt_cyan",
      "colouredstuff:farmland_cyan",
      "colouredstuff:fence_planks_cyan",
      "colouredstuff:gate_planks_cyan",
      "colouredstuff:leaves_cyan",
      "colouredstuff:log_cyan",
      "colouredstuff:log_stripped_cyan",
      "colouredstuff:path_cyan",
      "colouredstuff:planks_cyan",
      "colouredstuff:sandstone_cyan",
      "colouredstuff:sapling_cyan",
      "colouredstuff:slab_brick_cyan",
      "colouredstuff:slab_cobblestone_cyan",
      "colouredstuff:slab_planks_cyan",
      "colouredstuff:slab_sandstone_cyan",
      "colouredstuff:slab_stone_bricks_cyan",
      "colouredstuff:slab_stone_cyan",
      "colouredstuff:smooth_sandstone_cyan",
      "colouredstuff:stairs_brick_cyan",
      "colouredstuff:stairs_cobblestone_cyan",
      "colouredstuff:stairs_planks_cyan",
      "colouredstuff:stairs_sandstone_cyan",
      "colouredstuff:stairs_stone_bricks_cyan",
      "colouredstuff:stairs_stone_cyan",
      "colouredstuff:stone_bricks_cyan",
      "colouredstuff:stone_cyan",
      "colouredstuff:wall_brick_cyan",
      "colouredstuff:wall_cobblestone_cyan",
      "colouredstuff:wall_planks_cyan",
      "colouredstuff:wall_sandstone_cyan",
      "colouredstuff:wall_stone_bricks_cyan",
      "colouredstuff:wall_stone_cyan",
      "create:oxidized_copper_shingle_slab",
      "create:oxidized_copper_shingle_stairs",
      "create:oxidized_copper_shingles",
      "create:oxidized_copper_tile_slab",
      "create:oxidized_copper_tile_stairs",
      "create:oxidized_copper_tiles",
      "create:waxed_oxidized_copper_shingle_slab",
      "create:waxed_oxidized_copper_shingle_stairs",
      "create:waxed_oxidized_copper_shingles",
      "create:waxed_oxidized_copper_tile_slab",
      "create:waxed_oxidized_copper_tile_stairs",
      "create:waxed_oxidized_copper_tiles",
      "cyclic:eye_redstone",
      "cyclic:eye_teleport",
      "enderio:ender_crystal",
      "enderio:ender_crystal_powder",
      "enderio:enderios",
      "enderio:powdered_ender_pearl",
      "forcecraft:cyan_force_furnace",
      "forcecraft:force_brick_cyan",
      "forcecraft:force_brick_cyan_slab",
      "forcecraft:force_brick_cyan_stairs",
      "forcecraft:force_cyan_torch",
      "friendsandfoes:oxidized_copper_button",
      "friendsandfoes:oxidized_lightning_rod",
      "friendsandfoes:waxed_oxidized_copper_button",
      "friendsandfoes:waxed_oxidized_lightning_rod",
      "minecraft:cyan_banner",
      "minecraft:cyan_bed",
      "minecraft:cyan_candle",
      "minecraft:cyan_carpet",
      "minecraft:cyan_concrete",
      "minecraft:cyan_concrete_powder",
      "minecraft:cyan_dye",
      "minecraft:cyan_glazed_terracotta",
      "minecraft:cyan_shulker_box",
      "minecraft:cyan_stained_glass",
      "minecraft:cyan_stained_glass_pane",
      "minecraft:cyan_terracotta",
      "minecraft:cyan_wool",
      "minecraft:ender_eye",
      "minecraft:ender_pearl",
      "minecraft:oxidized_copper",
      "minecraft:oxidized_cut_copper",
      "minecraft:oxidized_cut_copper_slab",
      "minecraft:oxidized_cut_copper_stairs",
      "minecraft:stripped_warped_stem",
      "minecraft:warped_planks",
      "minecraft:warped_stem",
      "minecraft:waxed_oxidized_copper",
      "minecraft:waxed_oxidized_cut_copper",
      "minecraft:waxed_oxidized_cut_copper_slab",
      "minecraft:waxed_oxidized_cut_copper_stairs",
      "mysticalagriculture:cyan_crop_essence",
      "mysticalagriculture:cyan_crop_seeds",
      "sf5_things:cyan_apple",
      "thermal:ender_pearl_dust",
      "tinted_torches:cyan_torch",
      "minecraft:recovery_compass",
      "minecraft:sculk_catalyst",
      "minecraft:glow_ink_sac",
      "minecraft:calibrated_sculk_sensor",
      "minecraft:sculk_sensor",
      "minecraft:sculk_shrieker",
      "minecraft:sculk_vein",
      "minecraft:sculk",
      "minecraft:echo_shard",
      "minecraft:prismarine_bricks",
      "minecraft:prismarine_brick_stairs",
      "minecraft:prismarine_brick_slab",
      "minecraft:prismarine_shard",
      "minecraft:prismarine_crystals",
      "thermal:sadiroot"
    ]
  }
}
